qsopop/__init__.py
qsopop/binned_qlfs.py
qsopop/glf.py
qsopop/glf_binned.py
qsopop/kcorrection.py
qsopop/lumfun.py
qsopop/lumfunfit.py
qsopop/plots.py
qsopop/qlf.py
qsopop/qlf_binned.py
qsopop/selfun.py
qsopop/survey.py
qsopop-0.0b1.dist-info/METADATA
qsopop-0.0b1.dist-info/WHEEL
qsopop-0.0b1.dist-info/licenses/LICENSE
qsopop-0.0b1.dist-info/RECORD
