Metadata-Version: 2.4
Name: qsopop
Version: 0.0b1
Summary: A quasar population modeling framework 
Project-URL: Repository, https://github.com/cosmic-dawn-group/qsopop
Project-URL: Issues, https://github.com/cosmic-dawn-group/qsopop/issues
Author-email: Jan-Torge Schindler <jan-torge.schindler@uni-hamburg.de>, Timo Kist <kist@strw.leidenuniv.nl>
License-Expression: BSD-3-Clause
License-File: LICENSE
Keywords: astrophysics,black hole mass function,luminosity function,modeling,population,quasars
Classifier: Development Status :: 4 - Beta
Classifier: Operating System :: OS Independent
Classifier: Programming Language :: Python :: 3
Requires-Python: >=3.11
Requires-Dist: astropy>=6.1.6
Requires-Dist: corner>=2.2.3
Requires-Dist: emcee>=3.1.6
Requires-Dist: jupyterlab>=4.3.0
Requires-Dist: matplotlib>=3.9.2
Requires-Dist: numpy>=2.0.2
Requires-Dist: pandas>=2.2.3
Requires-Dist: scipy>=1.14.1
Requires-Dist: tqdm>=4.67.0
